sort/__init__.py
sort/bubble_sort.py
sort/insertion_sort.py
sort/quick_sort.py
jessicalexander_sort-0.1.7.dist-info/LICENSE
jessicalexander_sort-0.1.7.dist-info/METADATA
jessicalexander_sort-0.1.7.dist-info/WHEEL
jessicalexander_sort-0.1.7.dist-info/top_level.txt
jessicalexander_sort-0.1.7.dist-info/RECORD
