Metadata-Version: 2.1
Name: jessicalexander-sort
Version: 0.1.7
Summary: Package that includes multiple sorting method
Home-page: https://github.com/jessicalexander/siwp2005_jessicalexander_sort
Author: Jessica A
Author-email: jessica.422023027@civitas.ukrida.ac.id
License: MIT
Classifier: Development Status :: 3 - Alpha
Classifier: Intended Audience :: Developers
Classifier: License :: OSI Approved :: MIT License
Classifier: Programming Language :: Python :: 3
Classifier: Programming Language :: Python :: 3.8
Classifier: Programming Language :: Python :: 3.9
Classifier: Programming Language :: Python :: 3.10
Classifier: Programming Language :: Python :: 3.11
Requires-Python: >=3.8
License-File: LICENSE
